rilz/__init__.py
rilz/client.py
rilz/exception.py
rilz/id.py
rilz/input_file.py
rilz/logger.py
rilz/permission.py
rilz/query.py
rilz/role.py
rilz/service.py
rilz/browser/__init__.py
rilz/browser/exceptions.py
rilz/browser/selenium.py
rilz/encoders/__init__.py
rilz/encoders/value_class_encoder.py
rilz/enums/__init__.py
rilz/enums/adapter.py
rilz/enums/authentication_factor.py
rilz/enums/authenticator_type.py
rilz/enums/browser.py
rilz/enums/build_runtime.py
rilz/enums/compression.py
rilz/enums/credit_card.py
rilz/enums/deployment_download_type.py
rilz/enums/execution_method.py
rilz/enums/flag.py
rilz/enums/framework.py
rilz/enums/image_format.py
rilz/enums/image_gravity.py
rilz/enums/index_type.py
rilz/enums/message_priority.py
rilz/enums/messaging_provider_type.py
rilz/enums/name.py
rilz/enums/o_auth_provider.py
rilz/enums/password_hash.py
rilz/enums/relation_mutate.py
rilz/enums/relationship_type.py
rilz/enums/runtime.py
rilz/enums/smtp_encryption.py
rilz/enums/vcs_deployment_type.py
rilz/services/__init__.py
rilz/services/account.py
rilz/services/avatars.py
rilz/services/databases.py
rilz/services/functions.py
rilz/services/graphql.py
rilz/services/health.py
rilz/services/locale.py
rilz/services/messaging.py
rilz/services/sites.py
rilz/services/storage.py
rilz/services/teams.py
rilz/services/tokens.py
rilz/services/users.py
rilz/vault/__init__.py
rilz/vault/exceptions.py
rilz/vault/models.py
rilz/vault/vault.py
rilz-11.0.9.dist-info/LICENSE
rilz-11.0.9.dist-info/METADATA
rilz-11.0.9.dist-info/WHEEL
rilz-11.0.9.dist-info/top_level.txt
rilz-11.0.9.dist-info/RECORD
