Metadata-Version: 2.1
Name: rilz
Version: 11.0.9
Summary: Rilz is an open-source self-hosted backend server that abstract and simplify complex and repetitive development tasks behind a very simple REST API
Home-page: https://rilck.com/support
Author: Rilz Team
Author-email: team@rilck.com
Maintainer: Rilz Team
Maintainer-email: team@rilck.com
License: BSD-3-Clause
Download-URL: https://github.com/rilckztech/rilz-sdk/archive/11.0.9.tar.gz
Platform: UNKNOWN
Classifier: Development Status :: 5 - Production/Stable
Classifier: Intended Audience :: Developers
Classifier: Environment :: Web Environment
Classifier: Topic :: Software Development
Classifier: License :: OSI Approved :: BSD License
Classifier: Programming Language :: Python :: 3
Classifier: Programming Language :: Python :: 3.5
Classifier: Programming Language :: Python :: 3.6
Classifier: Programming Language :: Python :: 3.7
Classifier: Programming Language :: Python :: 3.8
License-File: LICENSE
Requires-Dist: requests
Requires-Dist: loguru
Requires-Dist: webdriver-manager
Requires-Dist: selenium
Requires-Dist: hvac
